lightbeam/__init__.py
lightbeam/__main__.py
lightbeam/api.py
lightbeam/count.py
lightbeam/create.py
lightbeam/delete.py
lightbeam/fetch.py
lightbeam/hashlog.py
lightbeam/lightbeam.py
lightbeam/send.py
lightbeam/truncate.py
lightbeam/util.py
lightbeam/validate.py
lightbeam/resources/__init__.py
lightbeam/tests/suite.py
lightbeam-0.1.9.dist-info/licenses/LICENSE
lightbeam-0.1.9.dist-info/METADATA
lightbeam-0.1.9.dist-info/WHEEL
lightbeam-0.1.9.dist-info/dependency_links.txt
lightbeam-0.1.9.dist-info/entry_points.txt
lightbeam-0.1.9.dist-info/top_level.txt
lightbeam-0.1.9.dist-info/RECORD
