Metadata-Version: 2.4
Name: lightbeam
Version: 0.1.9
Summary: Sends JSONL data into an Ed-Fi API
Home-page: https://github.com/edanalytics/lightbeam
Download-URL: https://github.com/edanalytics/lightbeam/archive/0.0.1.tar.gz
Author: Tom Reitz
Author-email: treitz@edanalytics.org
License: Apache 2.0
Keywords: data,transmission,api,edfi
Classifier: Development Status :: 4 - Beta
Classifier: Environment :: Console
Classifier: Intended Audience :: Developers
Classifier: Intended Audience :: Information Technology
Classifier: Intended Audience :: Education
Classifier: License :: OSI Approved :: Apache Software License
Classifier: Operating System :: OS Independent
Classifier: Programming Language :: Python :: 3
Classifier: Topic :: Education
Classifier: Topic :: Office/Business
Classifier: Topic :: Scientific/Engineering
Classifier: Topic :: Utilities
Requires-Python: >=3
License-File: LICENSE
Requires-Dist: wheel
Requires-Dist: aiohttp>=3.8.1
Requires-Dist: aiohttp_retry>=2.8.3
Requires-Dist: jsonschema>=4.16.0
Requires-Dist: python_dateutil>=2.8.2
Requires-Dist: pyyaml>=6.0
Requires-Dist: requests>=2.28.1
Requires-Dist: setuptools>=44.0.0
Dynamic: author
Dynamic: author-email
Dynamic: classifier
Dynamic: description
Dynamic: description-content-type
Dynamic: download-url
Dynamic: home-page
Dynamic: keywords
Dynamic: license
Dynamic: license-file
Dynamic: requires-dist
Dynamic: requires-python
Dynamic: summary
